{"cameraMode":{"drawMode":0,"name":"Shaded","section":"Shading Mode"},"sceneLighting":true,"audioPlay":false,"sceneViewState":{"m_AlwaysRefresh":false,"showFog":true,"showSkybox":true,"showFlares":true,"showImageEffects":true,"showParticleSystems":true,"showVisualEffectGraphs":true,"m_FxEnabled":true},"in2DMode":false,"pivot":{"x":13.869630813598633,"y":26.618988037109376,"z":25.456096649169923},"rotation":{"x":-0.42510583996772768,"y":0.0776078850030899,"z":-0.03660459816455841,"w":-0.9010853171348572},"size":60.629493713378909,"orthographic":false}